{
	"id": "25bf610c-b5fb-4352-fb47-4964468d6ead",
	"name": "Arquisoft",
	"description": "",
	"order": [
		"9e16bf04-6be6-10e6-a9f5-3bf1758ecdf4",
		"bb0e54d2-f09c-7fd0-c922-5c689122a7a0",
		"41f1856f-9fce-4dac-5b44-e9e8a3a1654b",
		"08ca5780-9fb9-6e9f-77f5-9d9b474e7d5d",
		"50921ad0-3aab-98dd-e42b-cc142a604c4e",
		"95724679-60fa-6f2a-36e2-cd6008d3a54c",
		"29469082-b03a-a035-de42-fe7c994b0a68",
		"24d4f118-1c5f-e02e-5440-9bc425963eae"
	],
	"folders": [],
	"timestamp": 1487203960858,
	"owner": "",
	"public": false,
	"requests": [
		{
			"id": "08ca5780-9fb9-6e9f-77f5-9d9b474e7d5d",
			"headers": "Content-Type: application/json\n",
			"url": "http://localhost:8080/servidor/api/paciente/historial-fechas/1/1587207658406/1587207658406",
			"pathVariables": {},
			"preRequestScript": null,
			"method": "GET",
			"collectionId": "25bf610c-b5fb-4352-fb47-4964468d6ead",
			"data": [],
			"dataMode": "raw",
			"name": "http://localhost:8080/servidor/api/alertas/",
			"description": "Alertas en rango de fechas, no fechas encontradas",
			"descriptionFormat": "html",
			"time": 1487207816318,
			"version": 2,
			"responses": [],
			"tests": null,
			"currentHelper": "normal",
			"helperAttributes": {},
			"rawModeData": "{\n  \"esEmergencia\": true,\n  \"fecha\": \"2017-02-15T18:55:49.726-05:00\",\n  \"frecuenciaCardica\": 80,\n  \"idDispositivo\": 1,\n  \"nivelEstres\": 80,\n  \"presionSanguinea\": [\n    100,\n    90\n  ],\n  \"tipo\": 2,\n  \"ubicacion\": [\n    5,\n    8\n  ]\n}"
		},
		{
			"id": "24d4f118-1c5f-e02e-5440-9bc425963eae",
			"headers": "Content-Type: application/json\n",
			"url": "http://localhost:8080/servidor/api/paciente/1/historial",
			"pathVariables": {},
			"preRequestScript": null,
			"method": "GET",
			"collectionId": "25bf610c-b5fb-4352-fb47-4964468d6ead",
			"data": [],
			"dataMode": "raw",
			"name": "http://localhost:8080/servidor/api/alertas/",
			"description": "Get historial paciente",
			"descriptionFormat": "html",
			"time": 1487213736976,
			"version": 2,
			"responses": [],
			"tests": null,
			"currentHelper": "normal",
			"helperAttributes": {},
			"rawModeData": "{\n  \"alertas\": [],\n  \"examenes\": [\n    \"Examen 150\"\n  ],\n  \"paciente\": null,\n  \"tratamientos\": [\n    \"Tratamiento 150\"\n  ]\n}"
		},
		{
			"id": "29469082-b03a-a035-de42-fe7c994b0a68",
			"headers": "Content-Type: application/json\n",
			"url": "http://localhost:8080/servidor/api/paciente/1",
			"preRequestScript": null,
			"pathVariables": {},
			"method": "GET",
			"data": [],
			"dataMode": "raw",
			"version": 2,
			"tests": null,
			"currentHelper": "normal",
			"helperAttributes": {},
			"time": 1487213670094,
			"name": "http://localhost:8080/servidor/api/alertas/",
			"description": "Get historial paciente",
			"collectionId": "25bf610c-b5fb-4352-fb47-4964468d6ead",
			"responses": [],
			"rawModeData": "{\n  \"alertas\": [],\n  \"examenes\": [\n    \"Examen 150\"\n  ],\n  \"paciente\": null,\n  \"tratamientos\": [\n    \"Tratamiento 150\"\n  ]\n}"
		},
		{
			"id": "41f1856f-9fce-4dac-5b44-e9e8a3a1654b",
			"headers": "Content-Type: application/json\n",
			"url": "http://localhost:8080/servidor/api/paciente/historial-fechas/1/1287207658406/1587207658406",
			"pathVariables": {},
			"preRequestScript": null,
			"method": "GET",
			"collectionId": "25bf610c-b5fb-4352-fb47-4964468d6ead",
			"data": [],
			"dataMode": "raw",
			"name": "http://localhost:8080/servidor/api/alertas/",
			"description": "Alertas en rango de fechas",
			"descriptionFormat": "html",
			"time": 1487207790032,
			"version": 2,
			"responses": [],
			"tests": null,
			"currentHelper": "normal",
			"helperAttributes": {},
			"rawModeData": "{\n  \"esEmergencia\": true,\n  \"fecha\": \"2017-02-15T18:55:49.726-05:00\",\n  \"frecuenciaCardica\": 80,\n  \"idDispositivo\": 1,\n  \"nivelEstres\": 80,\n  \"presionSanguinea\": [\n    100,\n    90\n  ],\n  \"tipo\": 2,\n  \"ubicacion\": [\n    5,\n    8\n  ]\n}"
		},
		{
			"id": "50921ad0-3aab-98dd-e42b-cc142a604c4e",
			"headers": "Content-Type: application/json\n",
			"url": "http://localhost:8080/servidor/api/medico/consejo/1",
			"pathVariables": {},
			"preRequestScript": null,
			"method": "POST",
			"collectionId": "25bf610c-b5fb-4352-fb47-4964468d6ead",
			"data": [],
			"dataMode": "raw",
			"name": "http://localhost:8080/servidor/api/alertas/",
			"description": "Enviar consejo",
			"descriptionFormat": "html",
			"time": 1487208970136,
			"version": 2,
			"responses": [],
			"tests": null,
			"currentHelper": "normal",
			"helperAttributes": {},
			"rawModeData": "{\n  \"consejo\":\"Consejo 1\",\n  \"fecha\": \"2017-02-15T20:30:11.718-05:00\"\n}"
		},
		{
			"id": "95724679-60fa-6f2a-36e2-cd6008d3a54c",
			"headers": "Content-Type: application/json\n",
			"url": "http://localhost:8080/servidor/api/medico/configuracion/1",
			"pathVariables": {},
			"preRequestScript": null,
			"method": "POST",
			"collectionId": "25bf610c-b5fb-4352-fb47-4964468d6ead",
			"data": [],
			"dataMode": "raw",
			"name": "http://localhost:8080/servidor/api/alertas/",
			"description": "Enviar configuracion",
			"descriptionFormat": "html",
			"time": 1487209978765,
			"version": 2,
			"responses": [],
			"tests": null,
			"currentHelper": "normal",
			"helperAttributes": {},
			"rawModeData": "{\n  \"configuracion\":\"Configuracion 1\",\n  \"fecha\": \"2017-02-15T20:30:11.718-05:00\"\n}"
		},
		{
			"id": "9e16bf04-6be6-10e6-a9f5-3bf1758ecdf4",
			"headers": "Content-Type: application/json\n",
			"url": "http://localhost:8080/servidor/api/alertas/",
			"preRequestScript": null,
			"pathVariables": {},
			"method": "POST",
			"data": [],
			"dataMode": "raw",
			"tests": null,
			"currentHelper": "normal",
			"helperAttributes": {},
			"time": 1487204068403,
			"name": "http://localhost:8080/servidor/api/alertas/",
			"description": "No se genera alerta",
			"collectionId": "25bf610c-b5fb-4352-fb47-4964468d6ead",
			"responses": [],
			"rawModeData": "{\n  \"esEmergencia\": true,\n  \"fecha\": \"2017-02-15T18:55:49.726-05:00\",\n  \"frecuenciaCardica\": 80,\n  \"idDispositivo\": 1,\n  \"nivelEstres\": 10,\n  \"presionSanguinea\": [\n    100,\n    90\n  ],\n  \"tipo\": 2,\n  \"ubicacion\": [\n    5,\n    8\n  ]\n}"
		},
		{
			"id": "bb0e54d2-f09c-7fd0-c922-5c689122a7a0",
			"headers": "Content-Type: application/json\n",
			"url": "http://localhost:8080/servidor/api/alertas/",
			"preRequestScript": null,
			"pathVariables": {},
			"method": "POST",
			"data": [],
			"dataMode": "raw",
			"version": 2,
			"tests": null,
			"currentHelper": "normal",
			"helperAttributes": {},
			"time": 1487204058655,
			"name": "http://localhost:8080/servidor/api/alertas/",
			"description": "Si se genera alerta",
			"collectionId": "25bf610c-b5fb-4352-fb47-4964468d6ead",
			"responses": [],
			"rawModeData": "{\n  \"esEmergencia\": true,\n  \"fecha\": \"2017-02-15T18:55:49.726-05:00\",\n  \"frecuenciaCardica\": 80,\n  \"idDispositivo\": 1,\n  \"nivelEstres\": 80,\n  \"presionSanguinea\": [\n    100,\n    90\n  ],\n  \"tipo\": 2,\n  \"ubicacion\": [\n    5,\n    8\n  ]\n}"
		}
	]
}